{
  "sheetsById": {
    "Bouncing box": {
      "staticOverrides": {
        "byObject": {
          "Box": {
            "y": 25,
            "x": 31,
            "stretch": 1
          }
        }
      },
      "sequence": {
        "subUnitsPerUnit": 30,
        "length": 2,
        "type": "PositionalSequence",
        "tracksByObject": {
          "Box": {
            "trackData": {
              "yfHcdfprqB": {
                "type": "BasicKeyframedTrack",
                "keyframes": [
                  {
                    "id": "gofxmgjHgy",
                    "position": 0,
                    "connectedRight": true,
                    "handles": [
                      0.5,
                      1,
                      0.606171458545832,
                      0
                    ],
                    "value": 195
                  },
                  {
                    "id": "cNIRVEmOps",
                    "position": 0.933,
                    "connectedRight": true,
                    "handles": [
                      0.8352701219619694,
                      0.1726680588615613,
                      0.5,
                      0
                    ],
                    "value": 0
                  },
                  {
                    "id": "YDCo7e6Tfs",
                    "position": 1,
                    "connectedRight": true,
                    "handles": [
                      0.5,
                      1,
                      0.5,
                      0
                    ],
                    "value": 0
                  },
                  {
                    "id": "-SFL6raiv-",
                    "position": 1.167,
                    "connectedRight": true,
                    "handles": [
                      0.5,
                      1,
                      0.1709189082150157,
                      0.8854339291249698
                    ],
                    "value": 90
                  },
                  {
                    "id": "ntBfTaFa9g",
                    "position": 2,
                    "connectedRight": true,
                    "handles": [
                      0.47524152558912536,
                      1.0233173758071974,
                      0.5,
                      0
                    ],
                    "value": 195
                  }
                ]
              },
              "sOK0aMLGAh": {
                "type": "BasicKeyframedTrack",
                "keyframes": [
                  {
                    "id": "G21ZrBLoLW",
                    "position": 0,
                    "connectedRight": true,
                    "handles": [
                      0.5,
                      1,
                      0.5,
                      0
                    ],
                    "value": 1
                  },
                  {
                    "id": "HdcvLMxTZN",
                    "position": 0.8,
                    "connectedRight": true,
                    "handles": [
                      0.5,
                      1,
                      0.5,
                      0
                    ],
                    "value": 1
                  },
                  {
                    "id": "b9wRRp3-Vx",
                    "position": 1,
                    "connectedRight": true,
                    "handles": [
                      0.5,
                      1,
                      0.5,
                      0
                    ],
                    "value": 0.7
                  },
                  {
                    "id": "i07iRAzxKG",
                    "position": 1.167,
                    "connectedRight": true,
                    "handles": [
                      0.5,
                      1,
                      0.5,
                      0
                    ],
                    "value": 1.3
                  },
                  {
                    "id": "ufE2wAWMik",
                    "position": 1.533,
                    "connectedRight": true,
                    "handles": [
                      0.5,
                      1,
                      0.5,
                      0
                    ],
                    "value": 1.0064516129032257
                  }
                ]
              }
            },
            "trackIdByPropPath": {
              "[\"y\"]": "yfHcdfprqB",
              "[\"stretch\"]": "sOK0aMLGAh"
            }
          },
          "Dust": {
            "trackData": {
              "MgZwc6VBDZ": {
                "type": "BasicKeyframedTrack",
                "keyframes": [
                  {
                    "id": "BEqgzhib5Y",
                    "position": 0.9,
                    "connectedRight": true,
                    "handles": [
                      0.5,
                      1,
                      0.5,
                      0
                    ],
                    "value": 0
                  },
                  {
                    "id": "Q20x_SEgDt",
                    "position": 1.133,
                    "connectedRight": true,
                    "handles": [
                      0.5,
                      1,
                      0,
                      -0.013513513513513514
                    ],
                    "value": 1
                  },
                  {
                    "id": "tUQJYn_KnO",
                    "position": 1.633,
                    "connectedRight": true,
                    "handles": [
                      0.3009711953355393,
                      0.909053654245962,
                      0.5,
                      0
                    ],
                    "value": 0
                  }
                ]
              },
              "fUQeGLdAQ1": {
                "type": "BasicKeyframedTrack",
                "keyframes": [
                  {
                    "id": "NDWQioP6RU",
                    "position": 0.933,
                    "connectedRight": true,
                    "handles": [
                      0.5,
                      1,
                      0.07875324591226124,
                      0.9615384615384616
                    ],
                    "value": 0
                  },
                  {
                    "id": "_Eafp0W4p3",
                    "position": 1.967,
                    "connectedRight": true,
                    "handles": [
                      0.5,
                      1,
                      0.5,
                      0
                    ],
                    "value": 2.31
                  }
                ]
              }
            },
            "trackIdByPropPath": {
              "[\"opacity\"]": "MgZwc6VBDZ",
              "[\"scaleX\"]": "fUQeGLdAQ1"
            }
          }
        }
      }
    }
  },
  "definitionVersion": "0.4.0",
  "revisionHistory": [
    "PGxjD6TGeY1xHQiI",
    "kv5_eP-BR-KQT9xq",
    "syrsRpwkcEaW15DY",
    "HC8iDNTHWDUAujbt",
    "o3YF_KK5SiB_VNXg"
  ]
}